{"lands":{"autotiles":[{"k":[90,0,0,175,0],"v":{"id":2,"t":[0,0],"tid":318}},{"k":[91,0,0,174,0],"v":{"id":2,"t":[0,0],"tid":318}},{"k":[92,0,0,173,0],"v":{"id":2,"t":[0,0],"tid":318}},{"k":[93,0,0,172,0],"v":{"id":2,"t":[0,0],"tid":318}},{"k":[94,0,0,171,0],"v":{"id":2,"t":[0,0],"tid":318}},{"k":[95,0,0,170,0],"v":{"id":2,"t":[0,0],"tid":318}},{"k":[91,0,0,175,0],"v":{"id":2,"t":[0,0],"tid":318}},{"k":[92,0,0,174,0],"v":{"id":2,"t":[0,0],"tid":318}},{"k":[93,0,0,173,0],"v":{"id":2,"t":[0,0],"tid":318}},{"k":[94,0,0,172,0],"v":{"id":2,"t":[0,0],"tid":318}},{"k":[95,0,0,171,0],"v":{"id":2,"t":[0,0],"tid":318}},{"k":[88,0,0,175,0],"v":{"id":2,"t":[0,0],"tid":225}},{"k":[89,0,0,174,0],"v":{"id":2,"t":[0,0],"tid":225}},{"k":[90,0,0,173,0],"v":{"id":2,"t":[0,0],"tid":584}},{"k":[91,0,0,172,0],"v":{"id":2,"t":[0,0],"tid":62}},{"k":[92,0,0,171,0],"v":{"id":2,"t":[0,0],"tid":318}},{"k":[93,0,0,170,0],"v":{"id":2,"t":[0,0],"tid":318}},{"k":[94,0,0,169,0],"v":{"id":2,"t":[0,0],"tid":318}},{"k":[95,0,0,168,0],"v":{"id":2,"t":[0,0],"tid":318}},{"k":[89,0,0,175,0],"v":{"id":2,"t":[0,0],"tid":62}},{"k":[90,0,0,174,0],"v":{"id":2,"t":[0,0],"tid":62}},{"k":[91,0,0,173,0],"v":{"id":2,"t":[0,0],"tid":318}},{"k":[92,0,0,172,0],"v":{"id":2,"t":[0,0],"tid":318}},{"k":[93,0,0,171,0],"v":{"id":2,"t":[0,0],"tid":318}},{"k":[94,0,0,170,0],"v":{"id":2,"t":[0,0],"tid":318}},{"k":[95,0,0,169,0],"v":{"id":2,"t":[0,0],"tid":318}},{"k":[91,0,0,170,0],"v":{"id":2,"t":[0,0],"tid":225}},{"k":[92,0,0,169,0],"v":{"id":2,"t":[0,0],"tid":225}},{"k":[93,0,0,168,0],"v":{"id":2,"t":[0,0],"tid":584}},{"k":[94,0,0,167,0],"v":{"id":2,"t":[0,0],"tid":318}},{"k":[95,0,0,166,0],"v":{"id":2,"t":[0,0],"tid":318}},{"k":[90,0,0,172,0],"v":{"id":2,"t":[0,0],"tid":225}},{"k":[91,0,0,171,0],"v":{"id":2,"t":[0,0],"tid":584}},{"k":[92,0,0,170,0],"v":{"id":2,"t":[0,0],"tid":62}},{"k":[93,0,0,169,0],"v":{"id":2,"t":[0,0],"tid":62}},{"k":[94,0,0,168,0],"v":{"id":2,"t":[0,0],"tid":318}},{"k":[95,0,0,167,0],"v":{"id":2,"t":[0,0],"tid":318}},{"k":[93,0,0,166,0],"v":{"id":2,"t":[0,0],"tid":225}},{"k":[94,0,0,165,0],"v":{"id":2,"t":[0,0],"tid":225}},{"k":[95,0,0,164,0],"v":{"id":2,"t":[0,0],"tid":225}},{"k":[93,0,0,167,0],"v":{"id":2,"t":[0,0],"tid":584}},{"k":[94,0,0,166,0],"v":{"id":2,"t":[0,0],"tid":62}},{"k":[95,0,0,165,0],"v":{"id":2,"t":[0,0],"tid":62}},{"k":[94,0,0,175,0],"v":{"id":2,"t":[0,0],"tid":318}},{"k":[95,0,0,174,0],"v":{"id":2,"t":[0,0],"tid":318}},{"k":[95,0,0,175,0],"v":{"id":2,"t":[0,0],"tid":318}},{"k":[92,0,0,175,0],"v":{"id":2,"t":[0,0],"tid":318}},{"k":[93,0,0,174,0],"v":{"id":2,"t":[0,0],"tid":318}},{"k":[94,0,0,173,0],"v":{"id":2,"t":[0,0],"tid":318}},{"k":[95,0,0,172,0],"v":{"id":2,"t":[0,0],"tid":318}},{"k":[93,0,0,175,0],"v":{"id":2,"t":[0,0],"tid":318}},{"k":[94,0,0,174,0],"v":{"id":2,"t":[0,0],"tid":318}},{"k":[95,0,0,173,0],"v":{"id":2,"t":[0,0],"tid":318}}],"floors":[{"k":[80,0,0,175,0],"v":{"t":[0,0]}},{"k":[81,0,0,174,0],"v":{"t":[0,0]}},{"k":[82,0,0,173,0],"v":{"t":[0,0]}},{"k":[83,0,0,172,0],"v":{"t":[0,0]}},{"k":[84,0,0,171,0],"v":{"t":[0,0]}},{"k":[85,0,0,170,0],"v":{"t":[0,0]}},{"k":[86,0,0,169,0],"v":{"t":[0,0]}},{"k":[87,0,0,168,0],"v":{"t":[0,0]}},{"k":[88,0,0,167,0],"v":{"t":[0,0]}},{"k":[89,0,0,166,0],"v":{"t":[0,0]}},{"k":[90,0,0,165,0],"v":{"t":[0,0]}},{"k":[91,0,0,164,0],"v":{"t":[0,0]}},{"k":[92,0,0,163,0],"v":{"t":[0,0]}},{"k":[93,0,0,162,0],"v":{"t":[0,0]}},{"k":[94,0,0,161,0],"v":{"t":[0,0]}},{"k":[95,0,0,160,0],"v":{"t":[0,0]}},{"k":[81,0,0,175,0],"v":{"t":[0,0]}},{"k":[82,0,0,174,0],"v":{"t":[0,0]}},{"k":[83,0,0,173,0],"v":{"t":[0,0]}},{"k":[84,0,0,172,0],"v":{"t":[0,0]}},{"k":[85,0,0,171,0],"v":{"t":[0,0]}},{"k":[86,0,0,170,0],"v":{"t":[0,0]}},{"k":[87,0,0,169,0],"v":{"t":[0,0]}},{"k":[88,0,0,168,0],"v":{"t":[0,0]}},{"k":[89,0,0,167,0],"v":{"t":[0,0]}},{"k":[90,0,0,166,0],"v":{"t":[0,0]}},{"k":[91,0,0,165,0],"v":{"t":[0,0]}},{"k":[92,0,0,164,0],"v":{"t":[0,0]}},{"k":[93,0,0,163,0],"v":{"t":[0,0]}},{"k":[94,0,0,162,0],"v":{"t":[0,0]}},{"k":[95,0,0,161,0],"v":{"t":[0,0]}},{"k":[80,0,0,173,0],"v":{"t":[0,0]}},{"k":[81,0,0,172,0],"v":{"t":[0,0]}},{"k":[82,0,0,171,0],"v":{"t":[0,0]}},{"k":[83,0,0,170,0],"v":{"t":[0,0]}},{"k":[84,0,0,169,0],"v":{"t":[0,0]}},{"k":[85,0,0,168,0],"v":{"t":[0,0]}},{"k":[86,0,0,167,0],"v":{"t":[0,0]}},{"k":[87,0,0,166,0],"v":{"t":[0,0]}},{"k":[88,0,0,165,0],"v":{"t":[0,0]}},{"k":[89,0,0,164,0],"v":{"t":[0,0]}},{"k":[90,0,0,163,0],"v":{"t":[0,0]}},{"k":[91,0,0,162,0],"v":{"t":[0,0]}},{"k":[92,0,0,161,0],"v":{"t":[0,0]}},{"k":[93,0,0,160,0],"v":{"t":[0,0]}},{"k":[80,0,0,174,0],"v":{"t":[0,0]}},{"k":[81,0,0,173,0],"v":{"t":[0,0]}},{"k":[82,0,0,172,0],"v":{"t":[0,0]}},{"k":[83,0,0,171,0],"v":{"t":[0,0]}},{"k":[84,0,0,170,0],"v":{"t":[0,0]}},{"k":[85,0,0,169,0],"v":{"t":[0,0]}},{"k":[86,0,0,168,0],"v":{"t":[0,0]}},{"k":[87,0,0,167,0],"v":{"t":[0,0]}},{"k":[88,0,0,166,0],"v":{"t":[0,0]}},{"k":[89,0,0,165,0],"v":{"t":[0,0]}},{"k":[90,0,0,164,0],"v":{"t":[0,0]}},{"k":[91,0,0,163,0],"v":{"t":[0,0]}},{"k":[92,0,0,162,0],"v":{"t":[0,0]}},{"k":[93,0,0,161,0],"v":{"t":[0,0]}},{"k":[94,0,0,160,0],"v":{"t":[0,0]}},{"k":[80,0,0,171,0],"v":{"t":[0,0]}},{"k":[81,0,0,170,0],"v":{"t":[0,0]}},{"k":[82,0,0,169,0],"v":{"t":[0,0]}},{"k":[83,0,0,168,0],"v":{"t":[0,0]}},{"k":[84,0,0,167,0],"v":{"t":[0,0]}},{"k":[85,0,0,166,0],"v":{"t":[0,0]}},{"k":[86,0,0,165,0],"v":{"t":[0,0]}},{"k":[87,0,0,164,0],"v":{"t":[0,0]}},{"k":[88,0,0,163,0],"v":{"t":[0,0]}},{"k":[89,0,0,162,0],"v":{"t":[0,0]}},{"k":[90,0,0,161,0],"v":{"t":[0,0]}},{"k":[91,0,0,160,0],"v":{"t":[0,0]}},{"k":[80,0,0,172,0],"v":{"t":[0,0]}},{"k":[81,0,0,171,0],"v":{"t":[0,0]}},{"k":[82,0,0,170,0],"v":{"t":[0,0]}},{"k":[83,0,0,169,0],"v":{"t":[0,0]}},{"k":[84,0,0,168,0],"v":{"t":[0,0]}},{"k":[85,0,0,167,0],"v":{"t":[0,0]}},{"k":[86,0,0,166,0],"v":{"t":[0,0]}},{"k":[87,0,0,165,0],"v":{"t":[0,0]}},{"k":[88,0,0,164,0],"v":{"t":[0,0]}},{"k":[89,0,0,163,0],"v":{"t":[0,0]}},{"k":[90,0,0,162,0],"v":{"t":[0,0]}},{"k":[91,0,0,161,0],"v":{"t":[0,0]}},{"k":[92,0,0,160,0],"v":{"t":[0,0]}},{"k":[80,0,0,169,0],"v":{"t":[0,0]}},{"k":[81,0,0,168,0],"v":{"t":[0,0]}},{"k":[82,0,0,167,0],"v":{"t":[0,0]}},{"k":[83,0,0,166,0],"v":{"t":[0,0]}},{"k":[84,0,0,165,0],"v":{"t":[0,0]}},{"k":[85,0,0,164,0],"v":{"t":[0,0]}},{"k":[86,0,0,163,0],"v":{"t":[0,0]}},{"k":[87,0,0,162,0],"v":{"t":[0,0]}},{"k":[88,0,0,161,0],"v":{"t":[0,0]}},{"k":[89,0,0,160,0],"v":{"t":[0,0]}},{"k":[80,0,0,170,0],"v":{"t":[0,0]}},{"k":[81,0,0,169,0],"v":{"t":[0,0]}},{"k":[82,0,0,168,0],"v":{"t":[0,0]}},{"k":[83,0,0,167,0],"v":{"t":[0,0]}},{"k":[84,0,0,166,0],"v":{"t":[0,0]}},{"k":[85,0,0,165,0],"v":{"t":[0,0]}},{"k":[86,0,0,164,0],"v":{"t":[0,0]}},{"k":[87,0,0,163,0],"v":{"t":[0,0]}},{"k":[88,0,0,162,0],"v":{"t":[0,0]}},{"k":[89,0,0,161,0],"v":{"t":[0,0]}},{"k":[90,0,0,160,0],"v":{"t":[0,0]}},{"k":[90,0,0,171,0],"v":{"t":[7,0]}},{"k":[89,0,0,172,0],"v":{"t":[7,0]}},{"k":[86,0,0,175,0],"v":{"t":[0,0]}},{"k":[87,0,0,174,0],"v":{"t":[0,0]}},{"k":[88,0,0,173,0],"v":{"t":[0,0]}},{"k":[89,0,0,173,0],"v":{"t":[7,0]}},{"k":[88,0,0,174,0],"v":{"t":[7,0]}},{"k":[87,0,0,175,0],"v":{"t":[7,0]}},{"k":[92,0,0,167,0],"v":{"t":[7,0]}},{"k":[91,0,0,168,0],"v":{"t":[7,0]}},{"k":[84,0,0,175,0],"v":{"t":[0,0]}},{"k":[85,0,0,174,0],"v":{"t":[0,0]}},{"k":[86,0,0,173,0],"v":{"t":[0,0]}},{"k":[87,0,0,172,0],"v":{"t":[0,0]}},{"k":[88,0,0,171,0],"v":{"t":[0,0]}},{"k":[89,0,0,170,0],"v":{"t":[0,0]}},{"k":[90,0,0,169,0],"v":{"t":[0,0]}},{"k":[92,0,0,168,0],"v":{"t":[7,0]}},{"k":[91,0,0,169,0],"v":{"t":[7,0]}},{"k":[90,0,0,170,0],"v":{"t":[7,0]}},{"k":[85,0,0,175,0],"v":{"t":[0,0]}},{"k":[86,0,0,174,0],"v":{"t":[0,0]}},{"k":[87,0,0,173,0],"v":{"t":[0,0]}},{"k":[88,0,0,172,0],"v":{"t":[0,0]}},{"k":[89,0,0,171,0],"v":{"t":[0,0]}},{"k":[95,0,0,162,0],"v":{"t":[7,0]}},{"k":[82,0,0,175,0],"v":{"t":[0,0]}},{"k":[83,0,0,174,0],"v":{"t":[0,0]}},{"k":[84,0,0,173,0],"v":{"t":[0,0]}},{"k":[85,0,0,172,0],"v":{"t":[0,0]}},{"k":[86,0,0,171,0],"v":{"t":[0,0]}},{"k":[87,0,0,170,0],"v":{"t":[0,0]}},{"k":[88,0,0,169,0],"v":{"t":[0,0]}},{"k":[89,0,0,168,0],"v":{"t":[0,0]}},{"k":[90,0,0,167,0],"v":{"t":[0,0]}},{"k":[91,0,0,166,0],"v":{"t":[0,0]}},{"k":[92,0,0,165,0],"v":{"t":[0,0]}},{"k":[93,0,0,164,0],"v":{"t":[0,0]}},{"k":[94,0,0,163,0],"v":{"t":[0,0]}},{"k":[95,0,0,163,0],"v":{"t":[7,0]}},{"k":[94,0,0,164,0],"v":{"t":[7,0]}},{"k":[93,0,0,165,0],"v":{"t":[7,0]}},{"k":[92,0,0,166,0],"v":{"t":[7,0]}},{"k":[83,0,0,175,0],"v":{"t":[0,0]}},{"k":[84,0,0,174,0],"v":{"t":[0,0]}},{"k":[85,0,0,173,0],"v":{"t":[0,0]}},{"k":[86,0,0,172,0],"v":{"t":[0,0]}},{"k":[87,0,0,171,0],"v":{"t":[0,0]}},{"k":[88,0,0,170,0],"v":{"t":[0,0]}},{"k":[89,0,0,169,0],"v":{"t":[0,0]}},{"k":[90,0,0,168,0],"v":{"t":[0,0]}},{"k":[91,0,0,167,0],"v":{"t":[0,0]}},{"k":[80,0,0,160,0],"v":{"t":[0,0]}},{"k":[80,0,0,167,0],"v":{"t":[0,0]}},{"k":[81,0,0,166,0],"v":{"t":[0,0]}},{"k":[82,0,0,165,0],"v":{"t":[0,0]}},{"k":[83,0,0,164,0],"v":{"t":[0,0]}},{"k":[84,0,0,163,0],"v":{"t":[0,0]}},{"k":[85,0,0,162,0],"v":{"t":[0,0]}},{"k":[86,0,0,161,0],"v":{"t":[0,0]}},{"k":[87,0,0,160,0],"v":{"t":[0,0]}},{"k":[80,0,0,168,0],"v":{"t":[0,0]}},{"k":[81,0,0,167,0],"v":{"t":[0,0]}},{"k":[82,0,0,166,0],"v":{"t":[0,0]}},{"k":[83,0,0,165,0],"v":{"t":[0,0]}},{"k":[84,0,0,164,0],"v":{"t":[0,0]}},{"k":[85,0,0,163,0],"v":{"t":[0,0]}},{"k":[86,0,0,162,0],"v":{"t":[0,0]}},{"k":[87,0,0,161,0],"v":{"t":[0,0]}},{"k":[88,0,0,160,0],"v":{"t":[0,0]}},{"k":[80,0,0,165,0],"v":{"t":[0,0]}},{"k":[81,0,0,164,0],"v":{"t":[0,0]}},{"k":[82,0,0,163,0],"v":{"t":[0,0]}},{"k":[83,0,0,162,0],"v":{"t":[0,0]}},{"k":[84,0,0,161,0],"v":{"t":[0,0]}},{"k":[85,0,0,160,0],"v":{"t":[0,0]}},{"k":[80,0,0,166,0],"v":{"t":[0,0]}},{"k":[81,0,0,165,0],"v":{"t":[0,0]}},{"k":[82,0,0,164,0],"v":{"t":[0,0]}},{"k":[83,0,0,163,0],"v":{"t":[0,0]}},{"k":[84,0,0,162,0],"v":{"t":[0,0]}},{"k":[85,0,0,161,0],"v":{"t":[0,0]}},{"k":[86,0,0,160,0],"v":{"t":[0,0]}},{"k":[80,0,0,163,0],"v":{"t":[0,0]}},{"k":[81,0,0,162,0],"v":{"t":[0,0]}},{"k":[82,0,0,161,0],"v":{"t":[0,0]}},{"k":[83,0,0,160,0],"v":{"t":[0,0]}},{"k":[80,0,0,164,0],"v":{"t":[0,0]}},{"k":[81,0,0,163,0],"v":{"t":[0,0]}},{"k":[82,0,0,162,0],"v":{"t":[0,0]}},{"k":[83,0,0,161,0],"v":{"t":[0,0]}},{"k":[84,0,0,160,0],"v":{"t":[0,0]}},{"k":[80,0,0,161,0],"v":{"t":[0,0]}},{"k":[81,0,0,160,0],"v":{"t":[0,0]}},{"k":[80,0,0,162,0],"v":{"t":[0,0]}},{"k":[81,0,0,161,0],"v":{"t":[0,0]}},{"k":[82,0,0,160,0],"v":{"t":[0,0]}}]},"moun":{"a":[],"o":[]},"objs":{"list":[]},"objs3d":{"a":[],"o":[]},"sprites":{"list":[{"k":[84,0,0,175,0],"v":{"k":6,"t":[0,8,2,3]}},{"k":[80,0,0,160,0],"v":{"k":5,"t":[4,8,1,1]}},{"k":[83,0,0,175,0],"v":{"k":6,"t":[0,8,2,3]}},{"k":[86,0,0,167,0],"v":{"k":6,"t":[0,8,2,3]}},{"k":[85,0,0,160,0],"v":{"k":6,"t":[0,8,2,3]}}],"overflow":[],"walls":[]}}